odp/__init__.py
odp/__main__.py
odp/cli/__init__.py
odp/cli/main.py
odp/core/__init__.py
odp/core/detect_unused.py
odp/core/snowflake.py
odp/core/types.py
odp/py.typed
odp-0.3.1.dist-info/LICENSE
odp-0.3.1.dist-info/METADATA
odp-0.3.1.dist-info/WHEEL
odp-0.3.1.dist-info/entry_points.txt
odp-0.3.1.dist-info/RECORD
