Metadata-Version: 2.1
Name: odp
Version: 0.3.1
Summary: odp
Home-page: https://github.com/open-data-products/odp
Author: odp Authors
Author-email: fdexter@metalytics.dev
Requires-Python: >=3.8,<4.0
Classifier: Programming Language :: Python :: 3
Classifier: Programming Language :: Python :: 3.8
Classifier: Programming Language :: Python :: 3.9
Classifier: Programming Language :: Python :: 3.10
Classifier: Programming Language :: Python :: 3.11
Classifier: Programming Language :: Python :: 3.12
Requires-Dist: click (>=8.1.7,<9.0.0)
Requires-Dist: pydantic (>=2.7.1,<3.0.0)
Requires-Dist: python-dotenv (>=1.0.1,<2.0.0)
Requires-Dist: snowflake-connector-python (>=3.7.1,<4.0.0)
Requires-Dist: sqlglot (>=23.0.5,<24.0.0)
Project-URL: Documentation, https://open-data-products.github.io/odp/
Project-URL: Repository, https://github.com/open-data-products/odp
